fivetran_api_playground/__init__.py
fivetran_api_playground-1.1.0.dist-info/METADATA
fivetran_api_playground-1.1.0.dist-info/WHEEL
fivetran_api_playground-1.1.0.dist-info/entry_points.txt
fivetran_api_playground-1.1.0.dist-info/top_level.txt
fivetran_api_playground-1.1.0.dist-info/RECORD
