Metadata-Version: 2.4
Name: fivetran_api_playground
Version: 1.1.0
Summary: Fivetran API Examples to build custom connectors
Author-email: Fivetran <developers@fivetran.com>
Project-URL: Homepage, https://fivetran.com/
Project-URL: Github, https://github.com/fivetran
Project-URL: Changelog, https://fivetran.com/docs/connectors/connector-sdk/changelog
Classifier: Programming Language :: Python :: 3
Classifier: License :: OSI Approved :: MIT License
Classifier: Operating System :: OS Independent
Requires-Python: >=3.9
Requires-Dist: flask==3.1.1
Requires-Dist: faker==37.4.0
Requires-Dist: requests==2.32.4
